LICENSE
MANIFEST.in
README.rst
buildout.cfg
requirements.txt
setup.py
version.txt
bob/__init__.py
bob.db.hrf.egg-info/PKG-INFO
bob.db.hrf.egg-info/SOURCES.txt
bob.db.hrf.egg-info/dependency_links.txt
bob.db.hrf.egg-info/entry_points.txt
bob.db.hrf.egg-info/not-zip-safe
bob.db.hrf.egg-info/requires.txt
bob.db.hrf.egg-info/top_level.txt
bob/db/__init__.py
bob/db/hrf/__init__.py
bob/db/hrf/checkfiles.py
bob/db/hrf/create.py
bob/db/hrf/driver.py
bob/db/hrf/hrf_db_default.json
bob/db/hrf/hrf_test.csv
bob/db/hrf/hrf_train.csv
bob/db/hrf/models.py
bob/db/hrf/query.py
bob/db/hrf/test.py
doc/guide.rst
doc/index.rst
doc/links.rst
doc/py_api.rst
doc/img/bob-128x128.png
doc/img/bob-favicon.ico
doc/img/bob-logo.png